COPYING
MANIFEST.in
README.md
VERSION.txt
setup.py
dv/AedatFile.py
dv/Control.py
dv/Event.py
dv/EventFrameIterator.py
dv/Frame.py
dv/IMU.py
dv/LegacyAedatFile.py
dv/NetworkInput.py
dv/SocketInput.py
dv/Trigger.py
dv/__init__.py
dv.egg-info/PKG-INFO
dv.egg-info/SOURCES.txt
dv.egg-info/dependency_links.txt
dv.egg-info/not-zip-safe
dv.egg-info/requires.txt
dv.egg-info/top_level.txt
dv/fb/CompressionType.py
dv/fb/Constants.py
dv/fb/Event.py
dv/fb/EventPacket.py
dv/fb/FileDataDefinition.py
dv/fb/FileDataTable.py
dv/fb/Frame.py
dv/fb/FrameFormat.py
dv/fb/IMU.py
dv/fb/IMUPacket.py
dv/fb/IOHeader.py
dv/fb/PacketHeader.py
dv/fb/Trigger.py
dv/fb/TriggerPacket.py
dv/fb/TriggerType.py
dv/fb/__init__.py
dv/fb/util.py